xmlist.py
xmlist-1.2.dist-info/licenses/LICENSE
xmlist-1.2.dist-info/METADATA
xmlist-1.2.dist-info/WHEEL
xmlist-1.2.dist-info/top_level.txt
xmlist-1.2.dist-info/RECORD
