Metadata-Version: 2.4
Name: xmlist
Version: 1.2
Summary: Generates XML, represented as lists and tuples
Author-email: Joost Molenaar <jjm@j0057.nl>
License-Expression: MIT
Project-URL: repository, https://gitlab.com/j0057-git/python/xmlist
Project-URL: issues, https://gitlab.com/j0057-git/python/xmlist/-/issues
Keywords: xml,html
Classifier: Programming Language :: Python :: 3
Classifier: Programming Language :: Python :: 3 :: Only
Classifier: Programming Language :: Python :: Implementation :: CPython
Requires-Python: >=3.9
License-File: LICENSE
Dynamic: license-file
